CHANGES.txt
LICENSE.txt
MANIFEST.in
README.txt
setup.py
src/p01/__init__.py
src/p01.vocabulary.legacy.egg-info/PKG-INFO
src/p01.vocabulary.legacy.egg-info/SOURCES.txt
src/p01.vocabulary.legacy.egg-info/dependency_links.txt
src/p01.vocabulary.legacy.egg-info/namespace_packages.txt
src/p01.vocabulary.legacy.egg-info/not-zip-safe
src/p01.vocabulary.legacy.egg-info/requires.txt
src/p01.vocabulary.legacy.egg-info/top_level.txt
src/p01/vocabulary/__init__.py
src/p01/vocabulary/legacy/README.txt
src/p01/vocabulary/legacy/__init__.py
src/p01/vocabulary/legacy/i18nextract.py
src/p01/vocabulary/legacy/interfaces.py
src/p01/vocabulary/legacy/tests.py
src/p01/vocabulary/legacy/vocabulary.py